neodynamics/__init__.py
neodynamics/cli.py
neodynamics/interface/__init__.py
neodynamics/interface/agent/__init__.py
neodynamics/interface/agent/client.py
neodynamics/interface/agent/server_factory.py
neodynamics/interface/environment/__init__.py
neodynamics/interface/environment/client.py
neodynamics/interface/environment/server_factory.py
neodynamics/interface/generate.sh
neodynamics/interface/proto.proto
neodynamics/interface/proto_pb2.py
neodynamics/interface/proto_pb2.pyi
neodynamics/interface/proto_pb2_grpc.py
neodynamics/interface/utils.py
neodynamics/scripts/__init__.py
neodynamics/scripts/neodynamics_cli.py
neodynamics-0.1.14.dist-info/METADATA
neodynamics-0.1.14.dist-info/WHEEL
neodynamics-0.1.14.dist-info/entry_points.txt
neodynamics-0.1.14.dist-info/RECORD
