Metadata-Version: 2.3
Name: neodynamics
Version: 0.1.14
Summary: A package for dynamic systems simulation and Docker management
License: MIT
Requires-Python: >=3.7
Classifier: License :: OSI Approved :: MIT License
Classifier: Programming Language :: Python :: 3
Classifier: Programming Language :: Python :: 3.7
Classifier: Programming Language :: Python :: 3.8
Classifier: Programming Language :: Python :: 3.9
Classifier: Programming Language :: Python :: 3.10
Classifier: Programming Language :: Python :: 3.11
Classifier: Programming Language :: Python :: 3.12
Classifier: Programming Language :: Python :: 3.13
Requires-Dist: docker (>=6.0.0)
Requires-Dist: grpcio-tools
Requires-Dist: gymnasium
Requires-Dist: msgpack
